pyweek.py
pyweek-0.5.3.dist-info/LICENSE
pyweek-0.5.3.dist-info/METADATA
pyweek-0.5.3.dist-info/WHEEL
pyweek-0.5.3.dist-info/entry_points.txt
pyweek-0.5.3.dist-info/top_level.txt
pyweek-0.5.3.dist-info/RECORD
