Metadata-Version: 2.1
Name: pyweek
Version: 0.5.3
Summary: CLI for Pyweek.
Home-page: https://pyweek.org/
Author: Daniel Pope
Author-email: mauve@mauveweb.co.uk
License: UNKNOWN
Project-URL: Bug Tracker, https://github.com/pyweekorg/cli/issues
Project-URL: Documentation, https://pyweek.readthedocs.io/en/latest/cli.html
Project-URL: Source Code, https://github.com/pyweekorg/cli
Platform: UNKNOWN
Requires-Python: >=3.6
Requires-Dist: click
Requires-Dist: requests
Requires-Dist: progressbar2
Requires-Dist: packaging
Requires-Dist: colorama
